{
  "videos": [
    {
      "num": 118,
      "id": "6CdKb4EjBgM"
    },
    {
      "num": 51,
      "id": "RbOMUzAXksM"
    },
    {
      "num": 51,
      "id": "nd0Wc3QH9Lo"
    },
    {
      "num": 48,
      "id": "68gwy1W7Duo"
    },
    {
      "num": 42,
      "id": "CKtcsAVb-_Y"
    },
    {
      "num": 33,
      "id": "4jBP6nSfAUo"
    },
    {
      "num": 30,
      "id": "Loq6jhhexR4"
    },
    {
      "num": 30,
      "id": "CbyNk-802_g"
    },
    {
      "num": 30,
      "id": "tzGtJnhOSFg"
    },
    {
      "num": 27,
      "id": "nh--7UOAJMY"
    },
    {
      "num": 24,
      "id": "KT6WVJ3Ubvc"
    },
    {
      "num": 24,
      "id": "c5j06OQoRvU"
    },
    {
      "num": 24,
      "id": "c5j06OQoRvU"
    },
    {
      "num": 21,
      "id": "Zo3b8N4Fiw0"
    },
    {
      "num": 21,
      "id": "ex32CJG5NF8"
    },
    {
      "num": 21,
      "id": "ex32CJG5NF8"
    },
    {
      "num": 18,
      "id": "oUgpDRRwMrQ"
    },
    {
      "num": 18,
      "id": "4KHSZWUgobk"
    },
    {
      "num": 18,
      "id": "pGEV9alK8Z0"
    },
    {
      "num": 18,
      "id": "xEkOzxXNF4g"
    },
    {
      "num": 13,
      "id": "lsNF4KfmwkY"
    },
    {
      "num": 12,
      "id": "xJm1Q9zKAaQ"
    },
    {
      "num": 12,
      "id": "Q4hmjeauTBw"
    },
    {
      "num": 12,
      "id": "yA8cRPXjdJw"
    },
    {
      "num": 9,
      "id": "3H9jVZiqJFc"
    },
    {
      "num": 9,
      "id": "PZzXlvnoR5E"
    },
    {
      "num": 9,
      "id": "Og3nODyITSY"
    },
    {
      "num": 9,
      "id": "lP-dnTt5Q1s"
    },
    {
      "num": 9,
      "id": "Ko8QCaGHXVY"
    },
    {
      "num": 6,
      "id": "mrNraumzIhk"
    },
    {
      "num": 6,
      "id": "yZbYWJXjVq0"
    },
    {
      "num": 6,
      "id": "rBJZPvUJknE"
    },
    {
      "num": 6,
      "id": "3PbFBmMFTcE"
    },
    {
      "num": 6,
      "id": "Z-mMqKfpZ9Q"
    },
    {
      "num": 6,
      "id": "PasE03HUlqE"
    },
    {
      "num": 6,
      "id": "yCu_dqGNRZM"
    },
    {
      "num": 6,
      "id": "3iksTpFEUDU"
    },
    {
      "num": 6,
      "id": "ghupMCIf_aY"
    },
    {
      "num": 6,
      "id": "59VObkSvVLY"
    },
    {
      "num": 6,
      "id": "NlSfZM2WtIU"
    },
    {
      "num": 6,
      "id": "NlSfZM2WtIU"
    },
    {
      "num": 6,
      "id": "WazOE-3nd-8"
    },
    {
      "num": 6,
      "id": "WazOE-3nd-8"
    },
    {
      "num": 6,
      "id": "t9L13rQBOjE"
    },
    {
      "num": 6,
      "id": "mHox98NFU3o"
    },
    {
      "num": 3,
      "id": "ZL-xqqp7vJA"
    },
    {
      "num": 3,
      "id": "Jt6-yHXbmT4"
    },
    {
      "num": 3,
      "id": "B8ofyUNWzZg"
    },
    {
      "num": 3,
      "id": "jgHu05uLRvg"
    },
    {
      "num": 3,
      "id": "vu8VHgf3LVI"
    },
    {
      "num": 3,
      "id": "0A9rjxb8z1M"
    },
    {
      "num": 3,
      "id": "ugvQVKfpVvA"
    },
    {
      "num": 3,
      "id": "WlHeIo2JQsQ"
    },
    {
      "num": 3,
      "id": "2jo_9F7Dhww"
    },
    {
      "num": 3,
      "id": "JTxho9yT0js"
    },
    {
      "num": 3,
      "id": "ePZvnuy_f48"
    },
    {
      "num": 3,
      "id": "41I4tAz-lNE"
    },
    {
      "num": 3,
      "id": "xbEWtEzdTEU"
    },
    {
      "num": 3,
      "id": "ajYH8V5RdW0"
    },
    {
      "num": 3,
      "id": "Q-TyNdeoX9s"
    },
    {
      "num": 3,
      "id": "LzUaiwCRO6k"
    },
    {
      "num": 3,
      "id": "eaFcN1-k-dQ"
    },
    {
      "num": 3,
      "id": "OyWBRYXkTlM"
    },
    {
      "num": 3,
      "id": "YBE5Kuz7yJA"
    },
    {
      "num": 3,
      "id": "loL97JfStDI"
    },
    {
      "num": 3,
      "id": "CWNBqvXMx-M"
    },
    {
      "num": 3,
      "id": "ByptzVF5Hgk"
    },
    {
      "num": 3,
      "id": "_b20ORRsfJU"
    },
    {
      "num": 3,
      "id": "NExzfQFMU-o"
    },
    {
      "num": 3,
      "id": "VUCjh7uzMUc"
    },
    {
      "num": 3,
      "id": "HRiAF6ILpxw"
    },
    {
      "num": 3,
      "id": "HRiAF6ILpxw"
    },
    {
      "num": 3,
      "id": "kbzA_KotIxY"
    },
    {
      "num": 3,
      "id": "kbzA_KotIxY"
    },
    {
      "num": 3,
      "id": "68l8KucLPX4"
    },
    {
      "num": 3,
      "id": "68l8KucLPX4"
    },
    {
      "num": 3,
      "id": "jTDMOl7MvrU"
    },
    {
      "num": 3,
      "id": "jTDMOl7MvrU"
    },
    {
      "num": 3,
      "id": "ow-8qo3zkgg"
    },
    {
      "num": 3,
      "id": "0F8EZU6B-jE"
    }
  ]
}
